main.py
mseep_substack_reader-0.1.2.dist-info/METADATA
mseep_substack_reader-0.1.2.dist-info/WHEEL
mseep_substack_reader-0.1.2.dist-info/entry_points.txt
mseep_substack_reader-0.1.2.dist-info/top_level.txt
mseep_substack_reader-0.1.2.dist-info/RECORD
