Metadata-Version: 2.4
Name: mseep-substack-reader
Version: 0.1.2
Summary: Add your description here
Author-email: mseep <support@skydeck.ai>
Requires-Python: >=3.13
Requires-Dist: beautifulsoup4>=4.13.3
Requires-Dist: httpx>=0.28.1
Requires-Dist: mcp[cli]>=1.3.0
Requires-Dist: playwright>=1.50.0
